blocksmith/__init__.py
blocksmith/bitcoin.py
blocksmith/ethereum.py
blocksmith/generator.py
blocksmith-1.2.1.dist-info/METADATA
blocksmith-1.2.1.dist-info/RECORD
blocksmith-1.2.1.dist-info/WHEEL
blocksmith-1.2.1.dist-info/top_level.txt
